MANIFEST.in
setup.py
examples/via.py
examples/yie.txt
examples/sample/sss.py
wellsecurity/__init__.py
wellsecurity/middleware/__init__.py
wellsecurity/middleware/redis/__init__.py
wellsecurity/middleware/redis/publish.py
wellsecurity/middleware/redis/subscribe.py
wellsecurity/preprocessing/__init__.py
wellsecurity/preprocessing/wellsucutiry_dto.py
wellsecurity/preprocessing/cpu_memory_controller/__init__.py
wellsecurity/preprocessing/cpu_memory_controller/cpu_and_memory.py
wellsecurity/preprocessing/cpu_memory_controller/save_data.py
wellsecurity/preprocessing/cv2/__init__.py
wellsecurity/preprocessing/cv2/cv2play.py
wellsecurity/preprocessing/cv2/videoformattransfer.py
wellsecurity/preprocessing/cv2/videotransfer2.py
wellsecurity/preprocessing/dataprocessing/__init__.py
wellsecurity/preprocessing/dataprocessing/get_voc_class.py
wellsecurity/preprocessing/dataprocessing/split_training_testing_validation.py
wellsecurity/preprocessing/dataprocessing/voc2yolo.py
wellsecurity/preprocessing/testing/__init__.py
wellsecurity/preprocessing/testing/asynchronized.py
wellsecurity/preprocessing/testing/testing2106051115.py
wellsecurity/preprocessing/testing/testing_log.py
ws_common.egg-info/PKG-INFO
ws_common.egg-info/SOURCES.txt
ws_common.egg-info/dependency_links.txt
ws_common.egg-info/requires.txt
ws_common.egg-info/top_level.txt