Metadata-Version: 1.0
Name: ws-common
Version: 1.0.2.2107211640
Summary: ws common
Home-page: http://www.westwell-lab.com/
Author: Jianglin Zhang
Author-email: jianglin.zhang@westwell-lab.com
License: UNKNOWN
Platform: UNKNOWN
